hashlite/__init__.py
hashlite/decorators.py
hashlite/shell.py
hashlite/test_script.py
hashlite/utils.py
hashlite/version.py
hashlite-0.0.3.dist-info/DESCRIPTION.rst
hashlite-0.0.3.dist-info/METADATA
hashlite-0.0.3.dist-info/RECORD
hashlite-0.0.3.dist-info/WHEEL
hashlite-0.0.3.dist-info/entry_points.txt
hashlite-0.0.3.dist-info/metadata.json
hashlite-0.0.3.dist-info/top_level.txt
