Metadata-Version: 2.0
Name: hashlite
Version: 0.0.3
Summary: light weight json db implemented using python dicts
Home-page: https://github.com/samvarankashyap/hashlite
Author: samvaran kashyap rallabandi
Author-email: samvaran.kashyap@gmail.com
License: UNKNOWN
Platform: UNKNOWN
